fastapi_vue_setup.py
template/backend/__init__.py
template/backend/__main__.py
template/backend/app.py
template/frontend/vite-plugin-fastapi.js
template/scripts/devserver.py
template/scripts/fastapi-vue/build-frontend.py
template/scripts/fastapi-vue/buildutil.py
template/scripts/fastapi-vue/devutil.py
fastapi_vue_setup-0.6.0.dist-info/METADATA
fastapi_vue_setup-0.6.0.dist-info/WHEEL
fastapi_vue_setup-0.6.0.dist-info/entry_points.txt
fastapi_vue_setup-0.6.0.dist-info/RECORD
