Metadata-Version: 2.4
Name: fastapi-vue-setup
Version: 0.6.0
Summary: Tool to create or patch FastAPI+Vue projects with integrated build/dev systems
Project-URL: Homepage, https://git.zi.fi/LeoVasanko/fastapi-vue-setup
Project-URL: Repository, https://github.com/LeoVasanko/fastapi-vue-setup
Requires-Python: >=3.11
Requires-Dist: tomlkit>=0.12.0
